scegot/__init__.py
scegot/scegot.py
scegot-0.3.0.dist-info/LICENSE.txt
scegot-0.3.0.dist-info/METADATA
scegot-0.3.0.dist-info/WHEEL
scegot-0.3.0.dist-info/RECORD
