Metadata-Version: 2.3
Name: scegot
Version: 0.3.0
Summary: single cell trajectory inference framework based on Entropic Gaussian mixture Optimal Transport
License: MIT
Author: Toshiaki Yachimura
Author-email: toshiaki.yachimura.a4@tohoku.ac.jp
Requires-Python: >=3.11,<3.20
Classifier: License :: OSI Approved :: MIT License
Classifier: Programming Language :: Python :: 3
Classifier: Programming Language :: Python :: 3.11
Classifier: Programming Language :: Python :: 3.12
Classifier: Programming Language :: Python :: 3.13
Requires-Dist: POT (>=0.9.3,<0.10.0)
Requires-Dist: anndata (>=0.8,<0.9)
Requires-Dist: cellmap (>=1.0.7,<2.0.0)
Requires-Dist: graphviz (>=0.20.1,<0.21.0)
Requires-Dist: kaleido (==0.2.1)
Requires-Dist: llvmlite (>=0.44.0,<0.45.0)
Requires-Dist: matplotlib (>=3.8.0,<4.0.0)
Requires-Dist: natsort (>=8.4.0,<9.0.0)
Requires-Dist: networkx (>=3.2.1,<4.0.0)
Requires-Dist: numpy (>=1.26.3,<2.0.0)
Requires-Dist: pandas (>=2.2.0,<3.0.0)
Requires-Dist: plotly (>=5.18.0,<6.0.0)
Requires-Dist: pyarrow (>=18.0.0,<19.0.0)
Requires-Dist: pydotplus (>=2.0.2,<3.0.0)
Requires-Dist: scikit-learn (>=1.3.2,<2.0.0)
Requires-Dist: scipy (>=1.14.1,<2.0.0)
Requires-Dist: screcode (>=2.2.0,<3.0.0)
Requires-Dist: seaborn (>=0.13.1,<0.14.0)
Requires-Dist: tqdm (>=4.66.1,<5.0.0)
Requires-Dist: umap-learn (>=0.5.6,<0.6.0)
Project-URL: Documentation, https://yachimura-lab.github.io/scEGOT/tutorial.html
Project-URL: Homepage, https://yachimura-lab.github.io/scEGOT/
Project-URL: Repository, https://github.com/yachimura-lab/scEGOT
